resistant_kafka_avataa/__init__.py
resistant_kafka_avataa/common_exceptions.py
resistant_kafka_avataa/common_schemas.py
resistant_kafka_avataa/consumer.py
resistant_kafka_avataa/consumer_schemas.py
resistant_kafka_avataa/message_desirializers.py
resistant_kafka_avataa/message_serializers.py
resistant_kafka_avataa/producer.py
resistant_kafka_avataa/producer_schemas.py
resistant_kafka_avataa-0.9.5.dist-info/METADATA
resistant_kafka_avataa-0.9.5.dist-info/WHEEL
resistant_kafka_avataa-0.9.5.dist-info/top_level.txt
resistant_kafka_avataa-0.9.5.dist-info/RECORD
