Metadata-Version: 2.4
Name: resistant_kafka_avataa
Version: 0.9.5
Requires-Dist: confluent-kafka[protobuf,schemaregistry]==2.10.0
Requires-Dist: pydantic<3.0.0,>=1.10.21
Dynamic: description
Dynamic: description-content-type
Dynamic: requires-dist
